Metadata-Version: 2.1
Name: avro-helper-devlibx-v1
Version: 0.2.1
Summary: Python DSL for setting up Flask app CDC
Home-page: https://github.com/devlibx/avro-helper-py
Author: devlibx
Author-email: devlibxgithub@gmail.com
License: MIT
Requires-Dist: avro
